inspireapi/__init__.py
inspireapi/dtypes.py
inspireapi/main.py
inspireapi-0.0.2.dist-info/METADATA
inspireapi-0.0.2.dist-info/WHEEL
inspireapi-0.0.2.dist-info/top_level.txt
inspireapi-0.0.2.dist-info/RECORD
