Metadata-Version: 2.1
Name: inspireapi
Version: 0.0.2
Summary: Unofficial API for Inspire Investing's Insight API that provides Biblically responsible insights to securities
Home-page: https://github.com/carterjfulcher/inspireapi
Author: carterjfulcher
Author-email: fulcher.carter@gmail.com
License: MIT
Platform: any
